portfolio_manager/__init__.py
portfolio_manager/exceptions.py
portfolio_manager/portfolio.py
portfolio_manager/return_calculators.py
portfolio_manager-0.0.3.dist-info/LICENSE
portfolio_manager-0.0.3.dist-info/METADATA
portfolio_manager-0.0.3.dist-info/WHEEL
portfolio_manager-0.0.3.dist-info/top_level.txt
portfolio_manager-0.0.3.dist-info/RECORD
