Metadata-Version: 2.1
Name: portfolio-manager
Version: 0.0.3
Summary: Simple tool for monitoring the performance of investment portfolios.
Home-page: https://github.com/J-Curwell/portfolio-manager
Author: James Curwell -- George Calvert
Author-email: jamescurwell97@gmail.com
License: MIT
Platform: UNKNOWN
Classifier: Programming Language :: Python :: 3
Classifier: License :: OSI Approved :: MIT License
Classifier: Operating System :: OS Independent
Requires-Python: >=3.7
Requires-Dist: pandas
Requires-Dist: numpy
Requires-Dist: numpy-financial
